sbackup/__init__.py
sbackup-0.0.3.dist-info/LICENCE.txt
sbackup-0.0.3.dist-info/METADATA
sbackup-0.0.3.dist-info/WHEEL
sbackup-0.0.3.dist-info/top_level.txt
sbackup-0.0.3.dist-info/RECORD
