Metadata-Version: 2.1
Name: sbackup
Version: 0.0.3
Summary: Folder/File backup manager by seletive file extensions
Home-page: UNKNOWN
Author: Swarnadeep Seth
Author-email: swdseth@yahoo.com
License: UNKNOWN
Platform: UNKNOWN
Classifier: Programming Language :: Python :: 3
Classifier: License :: OSI Approved :: MIT License
Classifier: Operating System :: OS Independent
Requires-Python: >=3.6
